manage_django_crontab_manager_server.py
django_crontab_manager/__init__.py
django_crontab_manager/actions.py
django_crontab_manager/admin.py
django_crontab_manager/apps.py
django_crontab_manager/menus.py
django_crontab_manager/models.py
django_crontab_manager/services.py
django_crontab_manager/settings.py
django_crontab_manager/tests.py
django_crontab_manager/urls.py
django_crontab_manager/views.py
django_crontab_manager/locale/zh_Hans/LC_MESSAGES/django.mo
django_crontab_manager/locale/zh_Hans/LC_MESSAGES/django.po
django_crontab_manager/migrations/0001_initial.py
django_crontab_manager/migrations/__init__.py
django_crontab_manager/static/django-crontab-manager/css/django-crontab-manager.css
django_crontab_manager/templates/django_crontab_manager/output.html
django_crontab_manager-0.2.50.dist-info/licenses/LICENSE
django_crontab_manager_server/__init__.py
django_crontab_manager_server/settings.py
django_crontab_manager_server/urls.py
django_crontab_manager_server/wsgi.conf.py
django_crontab_manager_server/wsgi.py
django_crontab_manager-0.2.50.dist-info/METADATA
django_crontab_manager-0.2.50.dist-info/WHEEL
django_crontab_manager-0.2.50.dist-info/entry_points.txt
django_crontab_manager-0.2.50.dist-info/top_level.txt
django_crontab_manager-0.2.50.dist-info/RECORD
