Metadata-Version: 2.4
Name: django-crontab-manager
Version: 0.2.50
Summary: Manage crontab tasks on web. Update crontab file on system while changes made on manager. Work with django-crontab-agent.
Author: rRR0VrFP
Maintainer: rRR0VrFP
License: MIT
Keywords: django extensions
Classifier: Development Status :: 5 - Production/Stable
Classifier: Intended Audience :: Developers
Classifier: Topic :: Software Development :: Libraries :: Python Modules
Classifier: License :: OSI Approved :: MIT License
Classifier: Programming Language :: Python :: 3
Classifier: Programming Language :: Python :: 3 :: Only
License-File: LICENSE
Requires-Dist: PyYAML
Requires-Dist: bizerror>=0.4.7
Requires-Dist: fastutils>=0.39.8
Requires-Dist: django
Requires-Dist: django-extensions
Requires-Dist: django-app-requires
Requires-Dist: django-power-admin
Requires-Dist: django-fastadmin
Requires-Dist: django-horizontal-list-filter
Requires-Dist: django-admin-safe-login>=0.3.3
Requires-Dist: django-admin-global-sidebar>=0.1.3
Requires-Dist: django-simple-export-admin>=0.1.5
Requires-Dist: django-data-import-management>=0.1.5
Requires-Dist: django-safe-fields>=0.1.11
Requires-Dist: django-safe-settings>=0.1.1
Requires-Dist: django-apiview>=0.9.21
Requires-Dist: django-server-controller
Requires-Dist: whitenoise
Requires-Dist: psutil
Requires-Dist: python-dateutil
Dynamic: author
Dynamic: classifier
Dynamic: description
Dynamic: description-content-type
Dynamic: keywords
Dynamic: license
Dynamic: license-file
Dynamic: maintainer
Dynamic: requires-dist
Dynamic: summary
